README.md
license.txt
setup.cfg
setup.py
ejercicio13/__init__.py
ejercicio13/operaciones.py
ejercicio13mariosv.egg-info/PKG-INFO
ejercicio13mariosv.egg-info/SOURCES.txt
ejercicio13mariosv.egg-info/dependency_links.txt
ejercicio13mariosv.egg-info/top_level.txt