Metadata-Version: 2.1
Name: ejercicio13mariosv
Version: 1.0.0
Summary: Módulo que realiza operaciones matemáticas básicas
Author: Mario
Author-email: mariosueirovidal@gmail.com
License: MIT
Requires-Python: >=3.7
License-File: license.txt
